CHANGELOG.md
LICENSE.txt
MANIFEST.in
README.rst
setup.cfg
setup.py
conda/__init__.py
conda/__main__.py
conda/api.py
conda/compat.py
conda/config.py
conda/connection.py
conda/console.py
conda/egg_info.py
conda/exceptions.py
conda/exports.py
conda/fetch.py
conda/history.py
conda/install.py
conda/instructions.py
conda/lock.py
conda/logic.py
conda/misc.py
conda/plan.py
conda/resolve.py
conda/signature.py
conda/toposort.py
conda/utils.py
conda/version.py
conda.egg-info/PKG-INFO
conda.egg-info/SOURCES.txt
conda.egg-info/dependency_links.txt
conda.egg-info/entry_points.txt
conda.egg-info/not-zip-safe
conda.egg-info/pbr.json
conda.egg-info/requires.txt
conda.egg-info/top_level.txt
conda/_vendor/__init__.py
conda/_vendor/appdirs.py
conda/_vendor/auxlib/__init__.py
conda/_vendor/auxlib/collection.py
conda/_vendor/auxlib/compat.py
conda/_vendor/auxlib/configuration.py
conda/_vendor/auxlib/crypt.py
conda/_vendor/auxlib/decorators.py
conda/_vendor/auxlib/deprecation.py
conda/_vendor/auxlib/entity.py
conda/_vendor/auxlib/exceptions.py
conda/_vendor/auxlib/factory.py
conda/_vendor/auxlib/ish.py
conda/_vendor/auxlib/logz.py
conda/_vendor/auxlib/packaging.py
conda/_vendor/auxlib/path.py
conda/_vendor/auxlib/type_coercion.py
conda/_vendor/auxlib/_vendor/__init__.py
conda/_vendor/auxlib/_vendor/five.py
conda/_vendor/auxlib/_vendor/six.py
conda/_vendor/auxlib/_vendor/boltons/__init__.py
conda/_vendor/auxlib/_vendor/boltons/timeutils.py
conda/_vendor/boltons/__init__.py
conda/_vendor/boltons/setutils.py
conda/_vendor/progressbar/__init__.py
conda/_vendor/progressbar/compat.py
conda/_vendor/progressbar/widgets.py
conda/_vendor/toolz/__init__.py
conda/_vendor/toolz/_signatures.py
conda/_vendor/toolz/compatibility.py
conda/_vendor/toolz/dicttoolz.py
conda/_vendor/toolz/functoolz.py
conda/_vendor/toolz/itertoolz.py
conda/_vendor/toolz/recipes.py
conda/_vendor/toolz/utils.py
conda/_vendor/urllib3/__init__.py
conda/_vendor/urllib3/exceptions.py
conda/_vendor/urllib3/util/__init__.py
conda/_vendor/urllib3/util/url.py
conda/base/__init__.py
conda/base/constants.py
conda/base/context.py
conda/base/exceptions.py
conda/cli/__init__.py
conda/cli/activate.py
conda/cli/common.py
conda/cli/conda_argparse.py
