Metadata-Version: 1.1
Name: conda
Version: 4.3.13
Summary: OS-agnostic, system-level binary package manager.
Home-page: https://github.com/conda/conda
Author: Continuum Analytics, Inc.
Author-email: conda@continuum.io
License: BSD
Platform: UNKNOWN
Classifier: Development Status :: 5 - Production/Stable
Classifier: Intended Audience :: Developers
Classifier: Operating System :: OS Independent
Classifier: Programming Language :: Python :: 2
Classifier: Programming Language :: Python :: 2.7
Classifier: Programming Language :: Python :: 3
Classifier: Programming Language :: Python :: 3.4
Classifier: Programming Language :: Python :: 3.5
Classifier: Programming Language :: Python :: 3.6
